dash_excalidraw/DashExcalidraw.py
dash_excalidraw/__init__.py
dash_excalidraw/_imports_.py
dash_excalidraw/async-null.js
dash_excalidraw/async-null.js.map
dash_excalidraw/dash_excalidraw.min.js
dash_excalidraw/dash_excalidraw.min.js.map
dash_excalidraw/metadata.json
dash_excalidraw/package-info.json
dash_excalidraw-0.0.4.dist-info/LICENSE
dash_excalidraw-0.0.4.dist-info/METADATA
dash_excalidraw-0.0.4.dist-info/WHEEL
dash_excalidraw-0.0.4.dist-info/top_level.txt
dash_excalidraw-0.0.4.dist-info/RECORD
