Metadata-Version: 2.1
Name: dash-excalidraw
Version: 0.0.4
Summary: excalidraw interactive drawing and freeform component for dash.
Author: Pip Install Python <pipinstallpython@gmail.com>
License: MIT
Classifier: Framework :: Dash
License-File: LICENSE
